design/chiwen/test_run_dir/problems/Encoder/OneHotEncoder.v
module OneHotEncoder(
  input        clock,
  input        reset,
  input        io_in_0,
  input        io_in_1,
  input        io_in_2,
  input        io_in_3,
  input        io_in_4,
  input        io_in_5,
  input        io_in_6,
  input        io_in_7,
  input        io_in_8,
  input        io_in_9,
  input        io_in_10,
  input        io_in_11,
  input        io_in_12,
  input        io_in_13,
  input        io_in_14,
  input        io_in_15,
  output [3:0] io_out
);
  wire [3:0] _T_76; // @[OneHotEncoder.scala 12:94]
  wire [3:0] _T_78; // @[OneHotEncoder.scala 12:97]
  wire [3:0] _T_91; // @[OneHotEncoder.scala 12:94]
  wire [3:0] _T_93; // @[OneHotEncoder.scala 12:97]
  wire [3:0] _T_106; // @[OneHotEncoder.scala 12:94]
  wire [3:0] _T_108; // @[OneHotEncoder.scala 12:97]
  wire [3:0] _T_121; // @[OneHotEncoder.scala 12:94]
  wire [3:0] _T_123; // @[OneHotEncoder.scala 12:97]
  wire [3:0] _T_136; // @[OneHotEncoder.scala 12:94]
  wire [3:0] _T_138; // @[OneHotEncoder.scala 12:97]
  wire [3:0] _T_151; // @[OneHotEncoder.scala 12:94]
  wire [3:0] _T_153; // @[OneHotEncoder.scala 12:97]
  wire [3:0] _T_166; // @[OneHotEncoder.scala 12:94]
  wire [3:0] _T_168; // @[OneHotEncoder.scala 12:97]
  wire [3:0] _T_181; // @[OneHotEncoder.scala 12:94]
  wire [3:0] _T_183; // @[OneHotEncoder.scala 12:97]
  wire [3:0] _T_196; // @[OneHotEncoder.scala 12:94]
  wire [3:0] _T_198; // @[OneHotEncoder.scala 12:97]
  wire [3:0] _T_211; // @[OneHotEncoder.scala 12:94]
  wire [3:0] _T_213; // @[OneHotEncoder.scala 12:97]
  wire [3:0] _T_226; // @[OneHotEncoder.scala 12:94]
  wire [3:0] _T_228; // @[OneHotEncoder.scala 12:97]
  wire [3:0] _T_241; // @[OneHotEncoder.scala 12:94]
  wire [3:0] _T_243; // @[OneHotEncoder.scala 12:97]
  wire [3:0] _T_256; // @[OneHotEncoder.scala 12:94]
  wire [3:0] _T_258; // @[OneHotEncoder.scala 12:97]
  wire [3:0] _T_271; // @[OneHotEncoder.scala 12:94]
  wire [3:0] _T_273; // @[OneHotEncoder.scala 12:97]
  wire [3:0] _T_286; // @[OneHotEncoder.scala 12:94]
  wire [3:0] _T_290; // @[OneHotEncoder.scala 12:113]
  wire [3:0] _T_291; // @[OneHotEncoder.scala 12:113]
  wire [3:0] _T_292; // @[OneHotEncoder.scala 12:113]
  wire [3:0] _T_293; // @[OneHotEncoder.scala 12:113]
  wire [3:0] _T_294; // @[OneHotEncoder.scala 12:113]
  wire [3:0] _T_295; // @[OneHotEncoder.scala 12:113]
  wire [3:0] _T_296; // @[OneHotEncoder.scala 12:113]
  wire [3:0] _T_297; // @[OneHotEncoder.scala 12:113]
  wire [3:0] _T_298; // @[OneHotEncoder.scala 12:113]
  wire [3:0] _T_299; // @[OneHotEncoder.scala 12:113]
  wire [3:0] _T_300; // @[OneHotEncoder.scala 12:113]
  wire [3:0] _T_301; // @[OneHotEncoder.scala 12:113]
  wire [3:0] _T_302; // @[OneHotEncoder.scala 12:113]
  assign _T_76 = {io_in_1,io_in_1,io_in_1,io_in_1}; // @[OneHotEncoder.scala 12:94]
  assign _T_78 = _T_76 & 4'h1; // @[OneHotEncoder.scala 12:97]
  assign _T_91 = {io_in_2,io_in_2,io_in_2,io_in_2}; // @[OneHotEncoder.scala 12:94]
  assign _T_93 = _T_91 & 4'h2; // @[OneHotEncoder.scala 12:97]
  assign _T_106 = {io_in_3,io_in_3,io_in_3,io_in_3}; // @[OneHotEncoder.scala 12:94]
  assign _T_108 = _T_106 & 4'h3; // @[OneHotEncoder.scala 12:97]
  assign _T_121 = {io_in_4,io_in_4,io_in_4,io_in_4}; // @[OneHotEncoder.scala 12:94]
  assign _T_123 = _T_121 & 4'h4; // @[OneHotEncoder.scala 12:97]
  assign _T_136 = {io_in_5,io_in_5,io_in_5,io_in_5}; // @[OneHotEncoder.scala 12:94]
  assign _T_138 = _T_136 & 4'h5; // @[OneHotEncoder.scala 12:97]
  assign _T_151 = {io_in_6,io_in_6,io_in_6,io_in_6}; // @[OneHotEncoder.scala 12:94]
  assign _T_153 = _T_151 & 4'h6; // @[OneHotEncoder.scala 12:97]
  assign _T_166 = {io_in_7,io_in_7,io_in_7,io_in_7}; // @[OneHotEncoder.scala 12:94]
  assign _T_168 = _T_166 & 4'h7; // @[OneHotEncoder.scala 12:97]
  assign _T_181 = {io_in_8,io_in_8,io_in_8,io_in_8}; // @[OneHotEncoder.scala 12:94]
  assign _T_183 = _T_181 & 4'h8; // @[OneHotEncoder.scala 12:97]
  assign _T_196 = {io_in_9,io_in_9,io_in_9,io_in_9}; // @[OneHotEncoder.scala 12:94]
  assign _T_198 = _T_196 & 4'h9; // @[OneHotEncoder.scala 12:97]
  assign _T_211 = {io_in_10,io_in_10,io_in_10,io_in_10}; // @[OneHotEncoder.scala 12:94]
  assign _T_213 = _T_211 & 4'ha; // @[OneHotEncoder.scala 12:97]
  assign _T_226 = {io_in_11,io_in_11,io_in_11,io_in_11}; // @[OneHotEncoder.scala 12:94]
  assign _T_228 = _T_226 & 4'hb; // @[OneHotEncoder.scala 12:97]
  assign _T_241 = {io_in_12,io_in_12,io_in_12,io_in_12}; // @[OneHotEncoder.scala 12:94]
  assign _T_243 = _T_241 & 4'hc; // @[OneHotEncoder.scala 12:97]
  assign _T_256 = {io_in_13,io_in_13,io_in_13,io_in_13}; // @[OneHotEncoder.scala 12:94]
  assign _T_258 = _T_256 & 4'hd; // @[OneHotEncoder.scala 12:97]
  assign _T_271 = {io_in_14,io_in_14,io_in_14,io_in_14}; // @[OneHotEncoder.scala 12:94]
  assign _T_273 = _T_271 & 4'he; // @[OneHotEncoder.scala 12:97]
  assign _T_286 = {io_in_15,io_in_15,io_in_15,io_in_15}; // @[OneHotEncoder.scala 12:94]
  assign _T_290 = _T_78 | _T_93; // @[OneHotEncoder.scala 12:113]
  assign _T_291 = _T_290 | _T_108; // @[OneHotEncoder.scala 12:113]
  assign _T_292 = _T_291 | _T_123; // @[OneHotEncoder.scala 12:113]
  assign _T_293 = _T_292 | _T_138; // @[OneHotEncoder.scala 12:113]
  assign _T_294 = _T_293 | _T_153; // @[OneHotEncoder.scala 12:113]
  assign _T_295 = _T_294 | _T_168; // @[OneHotEncoder.scala 12:113]
  assign _T_296 = _T_295 | _T_183; // @[OneHotEncoder.scala 12:113]
  assign _T_297 = _T_296 | _T_198; // @[OneHotEncoder.scala 12:113]
  assign _T_298 = _T_297 | _T_213; // @[OneHotEncoder.scala 12:113]
  assign _T_299 = _T_298 | _T_228; // @[OneHotEncoder.scala 12:113]
  assign _T_300 = _T_299 | _T_243; // @[OneHotEncoder.scala 12:113]
  assign _T_301 = _T_300 | _T_258; // @[OneHotEncoder.scala 12:113]
  assign _T_302 = _T_301 | _T_273; // @[OneHotEncoder.scala 12:113]
  assign io_out = _T_302 | _T_286; // @[OneHotEncoder.scala 12:10]
endmodule

design/chiwen/test_run_dir/problems/Encoder/OneHotEncoder.vcd
$version Generated by VerilatedVcd $end
$date Sat Jan 12 13:44:31 2019
 $end
$timescale   1ns $end

 $scope module TOP $end
  $var wire  1 # clock $end
  $var wire  1 % io_in_0 $end
  $var wire  1 & io_in_1 $end
  $var wire  1 / io_in_10 $end
  $var wire  1 0 io_in_11 $end
  $var wire  1 1 io_in_12 $end
  $var wire  1 2 io_in_13 $end
  $var wire  1 3 io_in_14 $end
  $var wire  1 4 io_in_15 $end
  $var wire  1 ' io_in_2 $end
  $var wire  1 ( io_in_3 $end
  $var wire  1 ) io_in_4 $end
  $var wire  1 * io_in_5 $end
  $var wire  1 + io_in_6 $end
  $var wire  1 , io_in_7 $end
  $var wire  1 - io_in_8 $end
  $var wire  1 . io_in_9 $end
  $var wire  4 5 io_out [3:0] $end
  $var wire  1 $ reset $end
  $scope module OneHotEncoder $end
   $var wire  1 # clock $end
   $var wire  1 % io_in_0 $end
   $var wire  1 & io_in_1 $end
   $var wire  1 / io_in_10 $end
   $var wire  1 0 io_in_11 $end
   $var wire  1 1 io_in_12 $end
   $var wire  1 2 io_in_13 $end
   $var wire  1 3 io_in_14 $end
   $var wire  1 4 io_in_15 $end
   $var wire  1 ' io_in_2 $end
   $var wire  1 ( io_in_3 $end
   $var wire  1 ) io_in_4 $end
   $var wire  1 * io_in_5 $end
   $var wire  1 + io_in_6 $end
   $var wire  1 , io_in_7 $end
   $var wire  1 - io_in_8 $end
   $var wire  1 . io_in_9 $end
   $var wire  4 5 io_out [3:0] $end
   $var wire  1 $ reset $end
  $upscope $end
 $upscope $end
$enddefinitions $end


#0
0#
1$
0%
0&
0'
0(
0)
0*
0+
0,
0-
0.
0/
00
01
02
03
04
b0000 5
#1
1#
#2
0#
#3
1#
#4
0#
#5
1#
#6
0#
#7
1#
#8
0#
#9
1#
#10
0#
0$
1%
#11
1#
#12
0#
0%
1&
b0001 5
#13
1#
#14
0#
0&
1'
b0010 5
#15
1#
#16
0#
0'
1(
b0011 5
#17
1#
#18
0#
0(
1)
b0100 5
#19
1#
#20
0#
0)
1*
b0101 5
#21
1#
#22
0#
0*
1+
b0110 5
#23
1#
#24
0#
0+
1,
b0111 5
#25
1#
#26
0#
0,
1-
b1000 5
#27
1#
#28
0#
0-
1.
b1001 5
#29
1#
#30
0#
0.
1/
b1010 5
#31
1#
#32
0#
0/
10
b1011 5
#33
1#
#34
0#
00
11
b1100 5
#35
1#
#36
0#
01
12
b1101 5
#37
1#
#38
0#
02
13
b1110 5
#39
1#
#40
0#
03
14
b1111 5
